fds/__init__.py
fds/sdk/__init__.py
fds/sdk/ForeignExchangeRate/__init__.py
fds/sdk/ForeignExchangeRate/api_client.py
fds/sdk/ForeignExchangeRate/configuration.py
fds/sdk/ForeignExchangeRate/exceptions.py
fds/sdk/ForeignExchangeRate/model_utils.py
fds/sdk/ForeignExchangeRate/rest.py
fds/sdk/ForeignExchangeRate/api/__init__.py
fds/sdk/ForeignExchangeRate/api/forwards_api.py
fds/sdk/ForeignExchangeRate/api/spots_api.py
fds/sdk/ForeignExchangeRate/apis/__init__.py
fds/sdk/ForeignExchangeRate/model/__init__.py
fds/sdk/ForeignExchangeRate/model/error_response.py
fds/sdk/ForeignExchangeRate/model/error_response_sub_errors.py
fds/sdk/ForeignExchangeRate/model/forward.py
fds/sdk/ForeignExchangeRate/model/forward_period.py
fds/sdk/ForeignExchangeRate/model/forwards_request.py
fds/sdk/ForeignExchangeRate/model/forwards_response.py
fds/sdk/ForeignExchangeRate/model/frequency.py
fds/sdk/ForeignExchangeRate/model/ids.py
fds/sdk/ForeignExchangeRate/model/spot.py
fds/sdk/ForeignExchangeRate/model/spots_request.py
fds/sdk/ForeignExchangeRate/model/spots_response.py
fds/sdk/ForeignExchangeRate/models/__init__.py
fds.sdk.ForeignExchangeRate-1.0.13.dist-info/LICENSE
fds.sdk.ForeignExchangeRate-1.0.13.dist-info/METADATA
fds.sdk.ForeignExchangeRate-1.0.13.dist-info/WHEEL
fds.sdk.ForeignExchangeRate-1.0.13.dist-info/top_level.txt
fds.sdk.ForeignExchangeRate-1.0.13.dist-info/RECORD
